Metadata-Version: 2.1
Name: bestpkgabcdefg
Version: 0.0.1
Summary: code
Home-page: https://github.com/hylinux1024/niubiproject
Author: hylinux1024
Author-email: hylinux1024@gmail.com
License: UNKNOWN
Platform: UNKNOWN
Classifier: Programming Language :: Python :: 3
Classifier: License :: OSI Approved :: MIT License
Classifier: Operating System :: OS Independent
License-File: LICENSE
